MANIFEST.in
README.rst
setup.py
bin/pyscale
pyscale/__init__.py
pyscale.egg-info/PKG-INFO
pyscale.egg-info/SOURCES.txt
pyscale.egg-info/dependency_links.txt
pyscale.egg-info/requires.txt
pyscale.egg-info/top_level.txt
pyscale/files/module
pyscale/files/project/Cakefile
pyscale/files/project/app/.gitkeep
pyscale/files/project/config/__init__.py
pyscale/files/project/config/app.py
pyscale/files/project/lib/__init__.py
pyscale/files/project/lib/module.py
pyscale/files/project/logs/.gitkeep
pyscale/files/project/tests/.gitkeep
pyscale/files/project/tmp/pids/.gitkeep
pyscale/files/project/tmp/sockets/rpc/.gitkeep
pyscale/files/project/tools/console
pyscale/files/project/tools/logger
pyscale/lib/__init__.py
pyscale/lib/decorators.py
pyscale/lib/errors.py
pyscale/lib/log.py
pyscale/lib/module.py
pyscale/tools/__init__.py
pyscale/tools/console.py
pyscale/tools/generators.py
pyscale/tools/logger.py
pyscale/tools/tasks.py
pyscale/utils/__init__.py
pyscale/utils/commands.py
pyscale/utils/gevsubprocess/__init__.py
pyscale/utils/gevsubprocess/pipe.py
pyscale/zmq/__init__.py
pyscale/zmq/common.py
pyscale/zmq/multisocket.py
pyscale/zmq/rpc.py
pyscale/zmq/socket.py