Metadata-Version: 1.0
Name: pyscale
Version: 0.1.1
Summary: General purpose Python framework for writing highly scalable applications
Home-page: https://github.com/alexcepoi/pyscale
Author: Alexandru Cepoi
Author-email: alex.cepoi@gmail.com
License: GPLv3
Download-URL: https://github.com/alexcepoi/pyscale/zipball/master
Platform: linux
